pyaioredis/__init__.py
pyaioredis/client.py
pyaioredis/compat.py
pyaioredis/connection.py
pyaioredis/exceptions.py
pyaioredis/lock.py
pyaioredis/log.py
pyaioredis/py.typed
pyaioredis/sentinel.py
pyaioredis/utils.py
pyaioredis-1.0.0.dist-info/LICENSE
pyaioredis-1.0.0.dist-info/METADATA
pyaioredis-1.0.0.dist-info/WHEEL
pyaioredis-1.0.0.dist-info/top_level.txt
pyaioredis-1.0.0.dist-info/RECORD
