Metadata-Version: 2.1
Name: pyaioredis
Version: 1.0.0
Summary: asyncio (PEP 3156) Redis support
Home-page: https://github.com/aio-libs/aioredis-py
License: MIT
Platform: POSIX
Classifier: License :: OSI Approved :: MIT License
Classifier: Development Status :: 5 - Production/Stable
Classifier: Programming Language :: Python
Classifier: Programming Language :: Python :: 3
Classifier: Programming Language :: Python :: 3.6
Classifier: Programming Language :: Python :: 3.7
Classifier: Programming Language :: Python :: 3.8
Classifier: Programming Language :: Python :: 3.9
Classifier: Programming Language :: Python :: 3.10
Classifier: Programming Language :: Python :: 3.11
Classifier: Programming Language :: Python :: 3 :: Only
Classifier: Operating System :: POSIX
Classifier: Environment :: Web Environment
Classifier: Intended Audience :: Developers
Classifier: Topic :: Software Development
Classifier: Topic :: Software Development :: Libraries
Classifier: Framework :: AsyncIO
Requires-Python: >=3.8
License-File: LICENSE
Requires-Dist: async-timeout
Requires-Dist: typing-extensions
Provides-Extra: hiredis
Requires-Dist: hiredis (>=1.0) ; (implementation_name == "cpython") and extra == 'hiredis'
